reasonchain/__init__.py
reasonchain/agent.py
reasonchain/cot_pipeline.py
reasonchain/enviornment.py
reasonchain/faiss_vector_db.py
reasonchain/memory.py
reasonchain/task_utils.py
reasonchain/domain_templates/__init__.py
reasonchain/domain_templates/customer_support.py
reasonchain/domain_templates/ecommerce.py
reasonchain/domain_templates/education.py
reasonchain/domain_templates/energy.py
reasonchain/domain_templates/finance.py
reasonchain/domain_templates/gaming_entertainment.py
reasonchain/domain_templates/healthcare.py
reasonchain/domain_templates/hr_recruitment.py
reasonchain/domain_templates/legal.py
reasonchain/domain_templates/marketing.py
reasonchain/domain_templates/real_estate.py
reasonchain/domain_templates/retail.py
reasonchain/domain_templates/supply_chain.py
reasonchain/domain_templates/transportation.py
reasonchain/domain_templates/travel_hospitality.py
reasonchain/llm_models/__init__.py
reasonchain/llm_models/base_provider.py
reasonchain/llm_models/fine_tune.py
reasonchain/llm_models/model_manager.py
reasonchain/llm_models/provider_registry.py
reasonchain/llm_models/register_providers.py
reasonchain/llm_models/providers/__init__.py
reasonchain/llm_models/providers/anthropic_provider.py
reasonchain/llm_models/providers/custom_provider.py
reasonchain/llm_models/providers/groq_provider.py
reasonchain/llm_models/providers/ollama_provider.py
reasonchain/llm_models/providers/openai_provider.py
reasonchain/rag/Database_Readme.md
reasonchain/rag/__init__.py
reasonchain/rag/config.py
reasonchain/rag/rag_main.py
reasonchain/rag/adapters/__init__.py
reasonchain/rag/adapters/faiss_adapter.py
reasonchain/rag/adapters/milvus_adapter.py
reasonchain/rag/adapters/pinecone_adapter.py
reasonchain/rag/adapters/qdrant_adapter.py
reasonchain/rag/adapters/weaviate_adapter.py
reasonchain/rag/adapters/__pycache__/__init__.cpython-312.pyc
reasonchain/rag/adapters/__pycache__/faiss_adapter.cpython-312.pyc
reasonchain/rag/adapters/__pycache__/milvus_adapter.cpython-312.pyc
reasonchain-0.3.0.dist-info/licenses/LICENSE
reasonchain-0.3.0.dist-info/METADATA
reasonchain-0.3.0.dist-info/WHEEL
reasonchain-0.3.0.dist-info/top_level.txt
reasonchain-0.3.0.dist-info/RECORD
