Metadata-Version: 2.4
Name: reasonchain
Version: 0.3.0
Summary: A modular AI reasoning library for building intelligent agents.
Home-page: https://github.com/sunnybedi990/reasonchain
Author: Baljindersingh Bedi
Author-email: baljindersinghbedi409@gmail.com
License: MIT
Classifier: Development Status :: 4 - Beta
Classifier: Intended Audience :: Developers
Classifier: Programming Language :: Python :: 3.7
Classifier: Programming Language :: Python :: 3.8
Classifier: Programming Language :: Python :: 3.9
Classifier: Programming Language :: Python :: 3.10
Classifier: License :: OSI Approved :: MIT License
Classifier: Operating System :: OS Independent
Requires-Python: >=3.7
License-File: LICENSE
Requires-Dist: numpy<2.0.0,>=1.21.0
Requires-Dist: scipy<1.14.0,>=1.8.0
Requires-Dist: scikit-learn>=1.0.0
Requires-Dist: torch
Requires-Dist: tqdm
Requires-Dist: python-dotenv
Requires-Dist: psutil
Provides-Extra: all
Requires-Dist: numpy<2.0.0,>=1.21.0; extra == "all"
Requires-Dist: scipy<1.14.0,>=1.8.0; extra == "all"
Requires-Dist: scikit-learn>=1.0.0; extra == "all"
Requires-Dist: torch; extra == "all"
Requires-Dist: tqdm; extra == "all"
Requires-Dist: python-dotenv; extra == "all"
Requires-Dist: psutil; extra == "all"
Requires-Dist: faiss-cpu; extra == "all"
Requires-Dist: pymilvus>=2.0.0; extra == "all"
Requires-Dist: pinecone-client; extra == "all"
Requires-Dist: qdrant-client; extra == "all"
Requires-Dist: weaviate-client>=4.0.0; extra == "all"
Requires-Dist: transformers; extra == "all"
Requires-Dist: sentence-transformers; extra == "all"
Requires-Dist: ollama; extra == "all"
Requires-Dist: groq; extra == "all"
Requires-Dist: openai>=1.0.0; extra == "all"
Requires-Dist: matplotlib; extra == "all"
Requires-Dist: tabula-py; extra == "all"
Requires-Dist: camelot-py[cv]; extra == "all"
Requires-Dist: pymupdf; extra == "all"
Requires-Dist: tensorflow-hub; extra == "all"
Requires-Dist: gensim; extra == "all"
Requires-Dist: layoutparser; extra == "all"
Requires-Dist: pdf2image; extra == "all"
Requires-Dist: pytesseract; extra == "all"
Requires-Dist: pdfplumber; extra == "all"
Requires-Dist: fastapi[all]; extra == "all"
Requires-Dist: jpype1; extra == "all"
Requires-Dist: llama-index-core==0.12.2; extra == "all"
Requires-Dist: llama-parse; extra == "all"
Requires-Dist: llama-index-readers-file; extra == "all"
Requires-Dist: opencv-python; extra == "all"
Requires-Dist: datasets; extra == "all"
Requires-Dist: python-pptx; extra == "all"
Requires-Dist: moviepy; extra == "all"
Requires-Dist: SpeechRecognition; extra == "all"
Requires-Dist: ebooklib; extra == "all"
Requires-Dist: beautifulsoup4; extra == "all"
Requires-Dist: python-docx; extra == "all"
Requires-Dist: spacy; extra == "all"
Requires-Dist: striprtf; extra == "all"
Provides-Extra: core
Requires-Dist: numpy<2.0.0,>=1.21.0; extra == "core"
Requires-Dist: scipy<1.14.0,>=1.8.0; extra == "core"
Requires-Dist: scikit-learn>=1.0.0; extra == "core"
Requires-Dist: torch; extra == "core"
Requires-Dist: tqdm; extra == "core"
Requires-Dist: python-dotenv; extra == "core"
Requires-Dist: psutil; extra == "core"
Provides-Extra: db
Requires-Dist: faiss-cpu; extra == "db"
Requires-Dist: pymilvus>=2.0.0; extra == "db"
Requires-Dist: pinecone-client; extra == "db"
Requires-Dist: qdrant-client; extra == "db"
Requires-Dist: weaviate-client>=4.0.0; extra == "db"
Provides-Extra: llm
Requires-Dist: transformers; extra == "llm"
Requires-Dist: sentence-transformers; extra == "llm"
Requires-Dist: ollama; extra == "llm"
Requires-Dist: groq; extra == "llm"
Requires-Dist: openai>=1.0.0; extra == "llm"
Provides-Extra: rag
Requires-Dist: matplotlib; extra == "rag"
Requires-Dist: tabula-py; extra == "rag"
Requires-Dist: camelot-py[cv]; extra == "rag"
Requires-Dist: pymupdf; extra == "rag"
Requires-Dist: tensorflow-hub; extra == "rag"
Requires-Dist: gensim; extra == "rag"
Requires-Dist: layoutparser; extra == "rag"
Requires-Dist: pdf2image; extra == "rag"
Requires-Dist: pytesseract; extra == "rag"
Requires-Dist: pdfplumber; extra == "rag"
Requires-Dist: fastapi[all]; extra == "rag"
Requires-Dist: jpype1; extra == "rag"
Requires-Dist: llama-index-core==0.12.2; extra == "rag"
Requires-Dist: llama-parse; extra == "rag"
Requires-Dist: llama-index-readers-file; extra == "rag"
Requires-Dist: opencv-python; extra == "rag"
Requires-Dist: datasets; extra == "rag"
Requires-Dist: python-pptx; extra == "rag"
Requires-Dist: moviepy; extra == "rag"
Requires-Dist: SpeechRecognition; extra == "rag"
Requires-Dist: ebooklib; extra == "rag"
Requires-Dist: beautifulsoup4; extra == "rag"
Requires-Dist: python-docx; extra == "rag"
Requires-Dist: spacy; extra == "rag"
Requires-Dist: striprtf; extra == "rag"
Provides-Extra: dev
Requires-Dist: pytest; extra == "dev"
Requires-Dist: black; extra == "dev"
Requires-Dist: isort; extra == "dev"
Requires-Dist: flake8; extra == "dev"
Requires-Dist: mypy; extra == "dev"
Dynamic: author
Dynamic: author-email
Dynamic: classifier
Dynamic: description
Dynamic: description-content-type
Dynamic: home-page
Dynamic: license
Dynamic: license-file
Dynamic: provides-extra
Dynamic: requires-dist
Dynamic: requires-python
Dynamic: summary
